LICENSE
MANIFEST.in
README.rst
setup.py
bee_django_wiki/__init__.py
bee_django_wiki/admin.py
bee_django_wiki/apps.py
bee_django_wiki/decorators.py
bee_django_wiki/exports.py
bee_django_wiki/forms.py
bee_django_wiki/models.py
bee_django_wiki/tests.py
bee_django_wiki/urls.py
bee_django_wiki/utils.py
bee_django_wiki/views.py
bee_django_wiki.egg-info/PKG-INFO
bee_django_wiki.egg-info/SOURCES.txt
bee_django_wiki.egg-info/dependency_links.txt
bee_django_wiki.egg-info/requires.txt
bee_django_wiki.egg-info/top_level.txt
bee_django_wiki/migrations/0001_initial.py
bee_django_wiki/migrations/0001_initial.pyc
bee_django_wiki/migrations/0002_auto_20190903_1645.py
bee_django_wiki/migrations/0002_auto_20190903_1645.pyc
bee_django_wiki/migrations/0003_auto_20190903_1650.py
bee_django_wiki/migrations/0003_auto_20190903_1650.pyc
bee_django_wiki/migrations/0004_auto_20190903_1714.py
bee_django_wiki/migrations/0004_auto_20190903_1714.pyc
bee_django_wiki/migrations/0005_auto_20190903_1714.py
bee_django_wiki/migrations/0005_auto_20190903_1714.pyc
bee_django_wiki/migrations/0006_topicimage.py
bee_django_wiki/migrations/0006_topicimage.pyc
bee_django_wiki/migrations/0007_auto_20190903_1846.py
bee_django_wiki/migrations/0007_auto_20190903_1846.pyc
bee_django_wiki/migrations/0008_auto_20191122_1340.py
bee_django_wiki/migrations/0008_auto_20191122_1340.pyc
bee_django_wiki/migrations/0009_auto_20191122_1341.py
bee_django_wiki/migrations/0009_auto_20191122_1341.pyc
bee_django_wiki/migrations/__init__.py
bee_django_wiki/migrations/__init__.pyc
bee_django_wiki/static/bee_django_wiki/bootstrap/css/bootstrap-theme.min.css
bee_django_wiki/static/bee_django_wiki/bootstrap/css/bootstrap.min.css
bee_django_wiki/static/bee_django_wiki/bootstrap/fonts/glyphicons-halflings-regular.eot
bee_django_wiki/static/bee_django_wiki/bootstrap/fonts/glyphicons-halflings-regular.svg
bee_django_wiki/static/bee_django_wiki/bootstrap/fonts/glyphicons-halflings-regular.ttf
bee_django_wiki/static/bee_django_wiki/bootstrap/fonts/glyphicons-halflings-regular.woff
bee_django_wiki/static/bee_django_wiki/bootstrap/fonts/glyphicons-halflings-regular.woff2
